<?xml version="1.0" encoding="utf-8" ?>
<config>
  <parameter Name="ID" FieldName="Id" Width="0"  Desc="在用" />
  <parameter Name="项目ID" FieldName="ProjectId" Width="0"  Desc="在用" />
  <parameter Name="项目名称" FieldName="ProjectName"  Width="160"  Desc="在用" />
  <parameter Name="非任务表单ID" FieldName="FormId" Width="0"  Desc="在用" />
  <parameter Name="创建人ID" FieldName="InUser"  Width="0"  Desc="在用" />
  <parameter Name="创建人" FieldName="InUserName"  Width="150"  Desc="在用" />
  <parameter Name="创建时间" FieldName="InDate"  Width="160"  Desc="在用" IsSort="false"/>
  <parameter Name="编辑人ID" FieldName="EditUser"  Width="0"  Desc="在用" IsSort="false"/>
  <parameter Name="编辑人" FieldName="EditUserName"  Width="120"  Desc="在用" IsSort="false"/>
  <parameter Name="编辑时间" FieldName="EditDate"  Width="160"  Desc="在用" IsSort="false"/>
  <!--<parameter Name="删除人" FieldName="DelUser"  Width="150"  Desc="在用" />
  <parameter Name="删除时间" FieldName="DelDate"  Width="160"  Desc="在用" IsSort="false"/>
  <parameter Name="删除标记" FieldName="DelState"  Width="120"  Desc="在用" IsSort="false"/>-->
</config>