<?xml version="1.0" encoding="utf-8" ?>
<config>
  <parameter Name="ID" FieldName="Id" Width="0"  Desc="在用" />
  <parameter Name="程序Id" FieldName="DictypeId"  Width="0"  Desc="在用" />
  <parameter Name="所属分类" FieldName="DetailName"  Width="160"  Desc="在用" />
  <parameter Name="部门Id" FieldName="DepId"  Width="0"  Desc="在用" />
  <parameter Name="所属部门" FieldName="DepName"  Width="160"  Desc="在用" />
  <parameter Name="名称" FieldName="Name"  Width="260"  Desc="在用" />
  <parameter Name="版本" FieldName="Version"  Width="100"  Desc="在用" />
  <parameter Name="编号" FieldName="Code"  Width="150"  Desc="在用" />
  <parameter Name="描述" FieldName="Remark"  Width="240"  Desc="在用" />
  <parameter Name="创建人" FieldName="InUserName"  Width="80"  Desc="在用" />
  <parameter Name="创建时间" FieldName="InDate"  Width="140"  Desc="在用" />
  <parameter Name="修改人员" FieldName="EditUserName"  Width="80"  Desc="在用" IsSort="false"/>
  <parameter Name="修改日期" FieldName="EditDate"  Width="200"  Desc="在用" IsSort="false"/>
</config>